amara/__about__.py
amara/__init__.py
amara/cmodules/__init__.py
amara/iri/__init__.py
amara/iri/asynctools.py
amara/iri/inputsource.py
amara/iri/iri.py
amara/iri/irihelper.py
amara/iri/contrib/__init__.py
amara/iri/contrib/mem_check.py
amara/uxml/NOTES
amara/uxml/README.md
amara/uxml/__init__.py
amara/uxml/coax.py
amara/uxml/html5.py
amara/uxml/html5iter.py
amara/uxml/lex.py
amara/uxml/parser.py
amara/uxml/tree.py
amara/uxml/treeiter.py
amara/uxml/treeutil.py
amara/uxml/writer.py
amara/uxml/xml.py
amara/uxml/xmliter.py
amara/uxml/cli/__init__.py
amara/uxml/cli/microx.py
amara/uxml/xtron/README.md
amara/uxpath/README.md
amara/uxpath/__init__.py
amara/uxpath/functions.py
amara/uxpath/grammar.lark
amara/uxpath/lexrules.py
amara/uxpath/parserules.py
amara/uxpath/xast.py
amara-4.0.2.dist-info/METADATA
amara-4.0.2.dist-info/WHEEL
amara-4.0.2.dist-info/entry_points.txt
amara-4.0.2.dist-info/RECORD
