Metadata-Version: 2.4
Name: Amara
Version: 4.0.2
Summary: General-purpose web data processing library with IRI handling and MicroXML/XML processing
Project-URL: Documentation, https://github.com/OoriData/Amara#readme
Project-URL: Issues, https://github.com/OoriData/Amara/issues
Project-URL: Source, https://github.com/OoriData/Amara
Author-email: Uche Ogbuji <uche@oori.dev>
License-Expression: Apache-2.0
Keywords: data,html,iri,microxml,uri,url,web,xml
Classifier: Development Status :: 4 - Beta
Classifier: Intended Audience :: Developers
Classifier: Programming Language :: Python
Classifier: Programming Language :: Python :: 3.12
Classifier: Programming Language :: Python :: 3.13
Classifier: Programming Language :: Python :: Implementation :: CPython
Classifier: Topic :: Internet :: WWW/HTTP
Classifier: Topic :: Software Development :: Libraries :: Python Modules
Classifier: Topic :: Text Processing :: Markup :: HTML
Classifier: Topic :: Text Processing :: Markup :: XML
Requires-Python: >=3.12
Requires-Dist: html5lib-modern
Requires-Dist: nameparser
Requires-Dist: ply
Provides-Extra: dev
Requires-Dist: coverage[toml]>=6.5; extra == 'dev'
Requires-Dist: pytest-asyncio; extra == 'dev'
Requires-Dist: pytest-mock; extra == 'dev'
Requires-Dist: pytest>=7.0; extra == 'dev'
